middleware/__init__.py
middleware/command_manage_corpus_file.py
middleware/api/__init__.py
middleware/api/corpus_file_manger.py
middleware/downloader/__init__.py
middleware/downloader/http.py
middleware/settings/__init__.py
middleware/utils/__init__.py
middleware/utils/csv_merge.py
middleware/utils/file_util.py
middleware/utils/password.py
middleware/utils/time_util.py
corpus_middleware-0.2.9.dist-info/METADATA
corpus_middleware-0.2.9.dist-info/WHEEL
corpus_middleware-0.2.9.dist-info/entry_points.txt
corpus_middleware-0.2.9.dist-info/top_level.txt
corpus_middleware-0.2.9.dist-info/RECORD
